zcb_dbutils/__init__.py
zcb_dbutils/dbutils.py
zcb_dbutils-0.0.5.dist-info/LICENSE
zcb_dbutils-0.0.5.dist-info/METADATA
zcb_dbutils-0.0.5.dist-info/WHEEL
zcb_dbutils-0.0.5.dist-info/top_level.txt
zcb_dbutils-0.0.5.dist-info/RECORD
