Metadata-Version: 2.1
Name: zcb-dbutils
Version: 0.0.5
Summary: db utils with pymysql by chzcb
Home-page: https://github.com/chzcb/dbutils
Author: chzcb
Author-email: chzcb.04@163.com
License: MIT
Keywords: python,pymysql,zcb_dbutils
Classifier: Development Status :: 3 - Alpha
Classifier: Intended Audience :: Developers
Classifier: Programming Language :: Python :: 3
License-File: LICENSE
Requires-Dist: pymysql
